JavaguideMianshiTujiBan/README.md
JavaguideMianshiTujiBan/__init__.py
JavaguideMianshiTujiBan/__main__.py
JavaguideMianshiTujiBan/file.epub
JavaguideMianshiTujiBan/index.html
JavaguideMianshiTujiBan/css/__init__.py
JavaguideMianshiTujiBan/css/annotations.css
JavaguideMianshiTujiBan/css/main.css
JavaguideMianshiTujiBan/css/normalize.css
JavaguideMianshiTujiBan/css/popup.css
JavaguideMianshiTujiBan/font/__init__.py
JavaguideMianshiTujiBan/font/fontello.eot
JavaguideMianshiTujiBan/font/fontello.svg
JavaguideMianshiTujiBan/font/fontello.ttf
JavaguideMianshiTujiBan/font/fontello.woff
JavaguideMianshiTujiBan/img/__init__.py
JavaguideMianshiTujiBan/img/annotator-glyph-sprite.png
JavaguideMianshiTujiBan/img/annotator-icon-sprite.png
JavaguideMianshiTujiBan/img/apple-touch-icon.png
JavaguideMianshiTujiBan/img/cancelfullscreen.png
JavaguideMianshiTujiBan/img/close.png
JavaguideMianshiTujiBan/img/fullscreen.png
JavaguideMianshiTujiBan/img/loader.gif
JavaguideMianshiTujiBan/img/menu-icon.png
JavaguideMianshiTujiBan/img/save.png
JavaguideMianshiTujiBan/img/saved.png
JavaguideMianshiTujiBan/img/settings-s.png
JavaguideMianshiTujiBan/img/settings.png
JavaguideMianshiTujiBan/img/star.png
JavaguideMianshiTujiBan/js/__init__.py
JavaguideMianshiTujiBan/js/epub.js
JavaguideMianshiTujiBan/js/epub.min.js
JavaguideMianshiTujiBan/js/epub.min.map
JavaguideMianshiTujiBan/js/hooks.min.js
JavaguideMianshiTujiBan/js/hooks.min.map
JavaguideMianshiTujiBan/js/reader.js
JavaguideMianshiTujiBan/js/reader.js.map
JavaguideMianshiTujiBan/js/reader.min.js
JavaguideMianshiTujiBan/js/reader.min.map
JavaguideMianshiTujiBan/js/hooks/__init__.py
JavaguideMianshiTujiBan/js/hooks/extensions/__init__.py
JavaguideMianshiTujiBan/js/hooks/extensions/highlight.js
JavaguideMianshiTujiBan/js/libs/__init__.py
JavaguideMianshiTujiBan/js/libs/jquery.min.js
JavaguideMianshiTujiBan/js/libs/localforage.min.js
JavaguideMianshiTujiBan/js/libs/screenfull.js
JavaguideMianshiTujiBan/js/libs/screenfull.min.js
javaguide_mianshi_tuji_ban-2024.3.4.0.dist-info/METADATA
javaguide_mianshi_tuji_ban-2024.3.4.0.dist-info/WHEEL
javaguide_mianshi_tuji_ban-2024.3.4.0.dist-info/entry_points.txt
javaguide_mianshi_tuji_ban-2024.3.4.0.dist-info/top_level.txt
javaguide_mianshi_tuji_ban-2024.3.4.0.dist-info/RECORD
